{
  "id": "2025-02-11_ko_31",
  "headline": "Tilläggsanslag 17 miljoner kronor för lokalförsörjning",
  "summary": "Kommunstyrelsen beslutar att ge tilläggsanslag på totalt 17 miljoner kronor för kostnadsökningar och lokalförsörjningsobjekt.",
  "detail": "Ärendet omfattar tilläggsanslag och ombudgetering för kostnadsökningar och oförutsedda kostnader under budgetåret 2025. Tilläggsansklagen avser bland annat kompensation till nämnder för färdigställda lokalförsörjningsobjekt. Ombudgetering sker på grund av organisationsförändringar.\n\nTotalt beviljas 17 044 tkr i tilläggsanslag. Finansieringen sker ur Kommunstyrelsens utrymme samt från anslagen för beslutade konsekvenser av investeringar och lokalförsörjning.\n\nÖrebropartiet motsatte sig beslutet och hänvisade till sitt eget budgetförslag. Övriga partier godkände den förvaltningssamordnade propositionen.",
  "category": "budget",
  "contested": true,
  "location": null,
  "paragraph_ref": "§ 31",
  "tags": [
    "budget",
    "lokalförsörjning",
    "anslag"
  ],
  "voting": {
    "for": [
      "S",
      "M",
      "C",
      "L",
      "KD",
      "V",
      "MP"
    ],
    "against": [],
    "abstained": [
      "ÖrP"
    ],
    "result": "Bifall"
  },
  "quote": "Tilläggsanslag beviljas med totalt 17 044 tkr enligt Kommunledningsförvaltningens förslag.",
  "quote_page": "s. 6",
  "meeting": {
    "id": "2025-02-11_Kommunstyrelsen",
    "date": "2025-02-11",
    "type": "",
    "source_url": "/Users/gabriellinton/Desktop/kommun-monitor/data/pdfs/2025-02-11_Kommunstyrelsen.pdf"
  },
  "municipality": "orebro",
  "_links": {
    "self": "https://lingabton.github.io/kommun-monitor/api/v1/decisions/2025-02-11_ko_31.json",
    "meeting": "https://lingabton.github.io/kommun-monitor/api/v1/meetings/2025-02-11_Kommunstyrelsen.json",
    "web_url": "https://lingabton.github.io/kommun-monitor/beslut/2025-02-11_ko_31/"
  }
}